oasysdb-0.6.1.dist-info/METADATA
oasysdb-0.6.1.dist-info/WHEEL
oasysdb/__init__.py
oasysdb/py.typed
oasysdb/prelude.pyi
oasysdb/database.pyi
oasysdb/collection.pyi
oasysdb/vector.pyi
oasysdb/oasysdb.cpython-312-aarch64-linux-gnu.so
oasysdb-0.6.1.dist-info/RECORD
