Metadata-Version: 2.3
Name: oasysdb
Version: 0.6.1
Classifier: Intended Audience :: Developers
Classifier: License :: OSI Approved :: Apache Software License
Classifier: Programming Language :: Rust
Classifier: Topic :: Database
Classifier: Topic :: Text Processing :: Indexing
Summary: Fast & flexible embedded vector database with incremental HNSW indexing.
Keywords: embedded,vector,database,hnsw,ann
Home-Page: https://docs.oasysdb.com
Author: Edwin Kys, Oasys
License: Apache-2.0
Requires-Python: >=3.8
Project-URL: repository, https://github.com/oasysai/oasysdb
Project-URL: issues, https://github.com/oasysai/oasysdb/issues
Project-URL: changelog, https://github.com/oasysai/oasysdb/blob/main/docs/changelog.md
